Workbook

Sheet Assumptions
A1: PROJECT MERIDIAN | LBO MODEL
A2: Hypothetical sponsor acquisition of Spire Healthcare Group plc | GBP millions unless stated
A4: Assumption | B4: Value | C4: Units | D4: Comment
A5: LTM Revenue | B5: 1579.8 | C5: £m | D5: FY2025 reported revenue; source: Spire 2025 Annual Report
A6: LTM Adjusted EBITDA | B6: 268.6 | C6: £m | D6: FY2025 reported adjusted EBITDA; source: Spire 2025 Annual Report
A7: Prior-year Revenue | B7: =B5/(1+4.5%) -> 1511.7703 | C7: £m | D7: Implied from reported FY2025 revenue growth of 4.5%; approximate
A8: Prior-year Adjusted EBITDA | B8: 260 | C8: £m | D8: FY2024 comparative reported in Spire 2025 Annual Report
A9: Entry EV / EBITDA | B9: 10 | C9: x | D9: Illustrative assumption; not a market quote or fairness opinion
A10: Entry Debt / EBITDA | B10: 5 | C10: x | D10: Illustrative financing assumption; subject to lender diligence
A11: Transaction Fees | B11: 0.02 | C11: % of Entry EV | D11: Illustrative assumption
A12: Forecast Revenue Growth | B12: 0.045 | C12: % | D12: Illustrative base case, informed by FY2025 reported growth; not guidance
A13: EBITDA Margin Improvement | B13: 0.0025 | C13: % points per year | D13: Illustrative annual margin expansion
A14: Maintenance Capex | B14: 0.045 | C14: % of revenue | D14: Illustrative assumption; validate against reported cash flow/capex
A15: Cash Tax Rate | B15: 0.25 | C15: % | D15: Illustrative normalized tax assumption
A16: Cash Interest Rate | B16: 0.075 | C16: % | D16: Illustrative blended cash interest assumption
A17: Minimum Cash Balance | B17: 20 | C17: £m | D17: Illustrative operating liquidity reserve
A18: Exit EV / EBITDA | B18: 9 | C18: x | D18: Illustrative exit multiple; one turn below entry
A19: Hold Period | B19: 5 | C19: years | D19: Illustrative five-year sponsor hold
... A21: Working Capital Investment | B21: 0.005 | C21: % of incremental revenue | D21: Illustrative cash investment assumption
A24: Important limitation | B24: Screening model only. Entry EV is used as the acquisition funding base; existing debt, cash, lease liabilities, refinancing, minority interests, pension items, taxes, and detailed sources-and-uses are not fully reconciled. Do not present as a transaction-ready model until these items are sourced and incorporated.

Sheet Historical
A1: HISTORICAL FINANCIAL ANCHORS
A2: Publicly reported figures vs. modelled assumptions are explicitly separated
A4: Metric | B4: FY2024 | C4: FY2025 | D4: Source / treatment
A5: Revenue (£m) | B5: =Assumptions!B7 -> 1511.7703 | C5: =Assumptions!B5 -> 1579.8 | D5: FY2024 implied from reported 4.5% growth; FY2025 reported
A6: Adjusted EBITDA (£m) | B6: =Assumptions!B8 -> 260 | C6: =Assumptions!B6 -> 268.6 | D6: Reported adjusted EBITDA
A7: Adjusted EBITDA margin | B7: =B6/B5 -> 0.1719838 | C7: =C6/C5 -> 0.17002152 | D7: Calculated from above
A8: Revenue growth | C8: =C5/B5-1 -> 0.045 | D8: FY2025 reported growth stated as 4.5%; calculation may differ due to rounding
A11: Data discipline | B11: Only the FY2025 revenue (£1,579.8m), FY2025 adjusted EBITDA (£268.6m), FY2024 adjusted EBITDA (£260.0m) and reported revenue growth (4.5%) are entered from the cited public summary. FY2024 revenue is mathematically implied, not directly transcribed. Other historical line items must be extracted from the annual report before expanding the model.

Sheet Operating Model
A1: OPERATING MODEL
A2: Five-year illustrative forecast | GBP millions
A4: Metric | B4: FY2025A | C4: FY2026E | D4: FY2027E | E4: FY2028E | F4: FY2029E | G4: FY2030E
A5: Revenue | B5: =Assumptions!B5 -> 1579.8 | C5: =B5*(1+Assumptions!B12) -> 1650.891 | D5: =C5*(1+Assumptions!B12) -> 1725.1811 | E5: =D5*(1+Assumptions!B12) -> 1802.8142 | F5: =E5*(1+Assumptions!B12) -> 1883.9409 | G5: =F5*(1+Assumptions!B12) -> 1968.7182
A6: Revenue growth | C6: =C5/B5-1 -> 0.045 | D6: =D5/C5-1 -> 0.045 | E6: =E5/D5-1 -> 0.045 | F6: =F5/E5-1 -> 0.045 | G6: =G5/F5-1 -> 0.045
A7: Adjusted EBITDA margin | B7: =Assumptions!B6/Assumptions!B5 -> 0.17002152 | C7: =B7+Assumptions!B13 -> 0.17252152 | D7: =C7+Assumptions!B13 -> 0.17502152 | E7: =D7+Assumptions!B13 -> 0.17752152 | F7: =E7+Assumptions!B13 -> 0.18002152 | G7: =F7+Assumptions!B13 -> 0.18252152
A8: Adjusted EBITDA | B8: =B5*B7 -> 268.6 | C8: =C5*C7 -> 284.81423 | D8: =D5*D7 -> 301.94382 | E8: =E5*E7 -> 320.03833 | F8: =F5*F7 -> 339.1499 | G8: =G5*G7 -> 359.33345
A9: D&A | B9: =B5*Assumptions!B20 -> 55.293 | C9: =C5*Assumptions!B20 -> 57.781185 | D9: =D5*Assumptions!B20 -> 60.381338 | E9: =E5*Assumptions!B20 -> 63.098499 | F9: =F5*Assumptions!B20 -> 65.937931 | G9: =G5*Assumptions!B20 -> 68.905138
A10: EBIT | B10: =B8-B9 -> 213.307 | C10: =C8-C9 -> 227.03304 | D10: =D8-D9 -> 241.56248 | E10: =E8-E9 -> 256.93983 | F10: =F8-F9 -> 273.21197 | G10: =G8-G9 -> 290.42831
A11: Maintenance capex | B11: =B5*Assumptions!B14 -> 71.091 | C11: =C5*Assumptions!B14 -> 74.290095 | D11: =D5*Assumptions!B14 -> 77.633149 | E11: =E5*Assumptions!B14 -> 81.126641 | F11: =F5*Assumptions!B14 -> 84.77734 | G11: =G5*Assumptions!B14 -> 88.59232
A12: Working capital investment | B12: 0 | C12: =MAX(0,(C5-B5)*Assumptions!B21) -> 0.355455 | D12: =MAX(0,(D5-C5)*Assumptions!B21) -> 0.37145047 | E12: =MAX(0,(E5-D5)*Assumptions!B21) -> 0.38816575 | F12: =MAX(0,(F5-E5)*Assumptions!B21) -> 0.4056332 | G12: =MAX(0,(G5-F5)*Assumptions!B21) -> 0.4238867
A14: Forecast note | B14: All forecast drivers are illustrative, not company guidance. Model assumes revenue growth, modest annual EBITDA margin improvement, capex as a percentage of revenue, and working capital investment tied to incremental sales. Replace with segment-level evidence and management guidance where available.

Sheet Debt Schedule
A1: DEBT SCHEDULE
A2: Simplified single-term-loan cash sweep | GBP millions
A4: Metric | B4: At Close | C4: FY2026E | D4: FY2027E | E4: FY2028E | F4: FY2029E | G4: FY2030E
A5: Opening debt | B5: =Assumptions!B6*Assumptions!B10 -> 1343 | C5: =B5 -> 1343 | D5: =C8 -> 1343 | E5: =D8 -> 1340.5577 | F5: =E8 -> 1329.9095 | G5: =F8 -> 1309.9267
A6: Cash interest | B6: 0 | C6: =C5*Assumptions!B16 -> 100.725 | D6: =D5*Assumptions!B16 -> 100.725 | E6: =E5*Assumptions!B16 -> 100.54183 | F6: =F5*Assumptions!B16 -> 99.743213 | G6: =G5*Assumptions!B16 -> 98.244503
A7: Cash available for debt paydown | B7: 0 | C7: =MAX(0,'Operating Model'!C8-'Operating Model'!C11-'Operating Model'!C12-'Operating Model'!C9-'Operating Model'!C10*Assumptions!B15-C6) -> 0 | D7: =MAX(0,'Operating Model'!D8-'Operating Model'!D11-'Operating Model'!D12-'Operating Model'!D9-'Operating Model'!D10*Assumptions!B15-D6) -> 2.4422619 | E7: =MAX(0,'Operating Model'!E8-'Operating Model'!E11-'Operating Model'!E12-'Operating Model'!E9-'Operating Model'!E10*Assumptions!B15-E6) -> 10.648235 | F7: =MAX(0,'Operating Model'!F8-'Operating Model'!F11-'Operating Model'!F12-'Operating Model'!F9-'Operating Model'!F10*Assumptions!B15-F6) -> 19.982795 | G7: =MAX(0,'Operating Model'!G8-'Operating Model'!G11-'Operating Model'!G12-'Operating Model'!G9-'Operating Model'!G10*Assumptions!B15-G6) -> 30.560521
A8: Closing debt | B8: =B5 -> 1343 | C8: =MAX(0,C5-C7) -> 1343 | D8: =MAX(0,D5-D7) -> 1340.5577 | E8: =MAX(0,E5-E7) -> 1329.9095 | F8: =MAX(0,F5-F7) -> 1309.9267 | G8: =MAX(0,G5-G7) -> 1279.3662
A9: Debt / EBITDA | B9: =B5/Assumptions!B6 -> 5 | C9: =C8/'Operating Model'!C8 -> 4.7153543 | D9: =D8/'Operating Model'!D8 -> 4.4397588 | E9: =E8/'Operating Model'!E8 -> 4.1554695 | F9: =F8/'Operating Model'!F8 -> 3.8623826 | G9: =G8/'Operating Model'!G8 -> 3.5603872
A12: Mechanics / limitations | B12: Simplified debt schedule. Interest is calculated on opening debt; cash available for paydown is an approximation and is not a full cash flow statement. It excludes detailed taxes, fees amortisation, mandatory amortisation, revolver mechanics, minimum-cash reconciliation and lease liabilities. Replace with a full cash flow build before relying on the output.

Sheet Returns
A1: SPONSOR RETURNS
A2: Illustrative gross equity returns before fund-level fees and carried interest
A4: Metric | B4: Entry | C4: Exit | D4: Formula / note
A5: Entry Enterprise Value | B5: =Assumptions!B6*Assumptions!B9 -> 2686 | D5: LTM EBITDA × entry multiple
A6: Transaction Fees | B6: =B5*Assumptions!B11 -> 53.72 | D6: Entry EV × fee assumption
A7: Entry Debt | B7: =Assumptions!B6*Assumptions!B10 -> 1343 | D7: LTM EBITDA × leverage assumption
A8: Sponsor Equity | B8: =B5+B6-B7 -> 1396.72 | D8: Entry EV + fees − debt; simplified
A9: Exit EBITDA | C9: ='Operating Model'!G8 -> 359.33345 | D9: FY2030E EBITDA
A10: Exit Enterprise Value | C10: =C9*Assumptions!B18 -> 3234.001 | D10: Exit EBITDA × exit multiple
A11: Exit Debt | C11: ='Debt Schedule'!G8 -> 1279.3662 | D11: Closing debt at end of hold
A12: Exit Equity Value | C12: =C10-C11 -> 1954.6348 | D12: Exit EV − exit debt; excludes cash / other claims
A13: MOIC | C13: =C12/B8 -> 1.3994464 | D13: Exit equity / sponsor equity
A14: Gross IRR | C14: =(C13)^(1/Assumptions!B19)-1 -> 0.069525777 | D14: Annualized return over hold period
A17: Interpretation | B17: Returns are highly sensitive to entry multiple, exit multiple, operating performance and debt repayment. Treat the result as a screening output only until purchase price bridge, existing debt/cash, leases, financing fees, tax, and cash flow mechanics are reconciled.

Sheet Sensitivity
A1: SENSITIVITY ANALYSIS
A2: Exit gross MOIC by entry and exit valuation multiple | simplified debt held constant to base case
A4: Entry EV / EBITDA → | B4: 8 | C4: 9 | D4: 10 | E4: 11 | F4: 12
A5: 7 | B5: =(('Operating Model'!G8*$A5-'Debt Schedule'!G8)/(Assumptions!B6*8+Assumptions!B6*8*Assumptions!B11-Assumptions!B6*Assumptions!B10)) -> 1.4561768 | C5: =(('Operating Model'!G8*$A5-'Debt Schedule'!G8)/(Assumptions!B6*9+Assumptions!B6*9*Assumptions!B11-Assumptions!B6*Assumptions!B10)) -> 1.1008418 | D5: =(('Operating Model'!G8*$A5-'Debt Schedule'!G8)/(Assumptions!B6*10+Assumptions!B6*10*Assumptions!B11-Assumptions!B6*Assumptions!B10)) -> 0.88490745 | E5: =(('Operating Model'!G8*$A5-'Debt Schedule'!G8)/(Assumptions!B6*11+Assumptions!B6*11*Assumptions!B11-Assumptions!B6*Assumptions!B10)) -> 0.73979401 | F5: =(('Operating Model'!G8*$A5-'Debt Schedule'!G8)/(Assumptions!B6*12+Assumptions!B6*12*Assumptions!B11-Assumptions!B6*Assumptions!B10)) -> 0.63556889
A6: 8 | B6: =(('Operating Model'!G8*$A6-'Debt Schedule'!G8)/(Assumptions!B6*8+Assumptions!B6*8*Assumptions!B11-Assumptions!B6*Assumptions!B10)) -> 1.8795317 | C6: =(('Operating Model'!G8*$A6-'Debt Schedule'!G8)/(Assumptions!B6*9+Assumptions!B6*9*Assumptions!B11-Assumptions!B6*Assumptions!B10)) -> 1.42089 | D6: =(('Operating Model'!G8*$A6-'Debt Schedule'!G8)/(Assumptions!B6*10+Assumptions!B6*10*Assumptions!B11-Assumptions!B6*Assumptions!B10)) -> 1.1421769 | E6: =(('Operating Model'!G8*$A6-'Debt Schedule'!G8)/(Assumptions!B6*11+Assumptions!B6*11*Assumptions!B11-Assumptions!B6*Assumptions!B10)) -> 0.95487462 | F6: =(('Operating Model'!G8*$A6-'Debt Schedule'!G8)/(Assumptions!B6*12+Assumptions!B6*12*Assumptions!B11-Assumptions!B6*Assumptions!B10)) -> 0.82034808
A7: 9 | B7: =(('Operating Model'!G8*$A7-'Debt Schedule'!G8)/(Assumptions!B6*8+Assumptions!B6*8*Assumptions!B11-Assumptions!B6*Assumptions!B10)) -> 2.3028865 | C7: =(('Operating Model'!G8*$A7-'Debt Schedule'!G8)/(Assumptions!B6*9+Assumptions!B6*9*Assumptions!B11-Assumptions!B6*Assumptions!B10)) -> 1.7409382 | D7: =(('Operating Model'!G8*$A7-'Debt Schedule'!G8)/(Assumptions!B6*10+Assumptions!B6*10*Assumptions!B11-Assumptions!B6*Assumptions!B10)) -> 1.3994464 | E7: =(('Operating Model'!G8*$A7-'Debt Schedule'!G8)/(Assumptions!B6*11+Assumptions!B6*11*Assumptions!B11-Assumptions!B6*Assumptions!B10)) -> 1.1699552 | F7: =(('Operating Model'!G8*$A7-'Debt Schedule'!G8)/(Assumptions!B6*12+Assumptions!B6*12*Assumptions!B11-Assumptions!B6*Assumptions!B10)) -> 1.0051273
A8: 10 | B8: =(('Operating Model'!G8*$A8-'Debt Schedule'!G8)/(Assumptions!B6*8+Assumptions!B6*8*Assumptions!B11-Assumptions!B6*Assumptions!B10)) -> 2.7262414 | C8: =(('Operating Model'!G8*$A8-'Debt Schedule'!G8)/(Assumptions!B6*9+Assumptions!B6*9*Assumptions!B11-Assumptions!B6*Assumptions!B10)) -> 2.0609863 | D8: =(('Operating Model'!G8*$A8-'Debt Schedule'!G8)/(Assumptions!B6*10+Assumptions!B6*10*Assumptions!B11-Assumptions!B6*Assumptions!B10)) -> 1.6567159 | E8: =(('Operating Model'!G8*$A8-'Debt Schedule'!G8)/(Assumptions!B6*11+Assumptions!B6*11*Assumptions!B11-Assumptions!B6*Assumptions!B10)) -> 1.3850358 | F8: =(('Operating Model'!G8*$A8-'Debt Schedule'!G8)/(Assumptions!B6*12+Assumptions!B6*12*Assumptions!B11-Assumptions!B6*Assumptions!B10)) -> 1.1899065
A9: 11 | B9: =(('Operating Model'!G8*$A9-'Debt Schedule'!G8)/(Assumptions!B6*8+Assumptions!B6*8*Assumptions!B11-Assumptions!B6*Assumptions!B10)) -> 3.1495963 | C9: =(('Operating Model'!G8*$A9-'Debt Schedule'!G8)/(Assumptions!B6*9+Assumptions!B6*9*Assumptions!B11-Assumptions!B6*Assumptions!B10)) -> 2.3810345 | D9: =(('Operating Model'!G8*$A9-'Debt Schedule'!G8)/(Assumptions!B6*10+Assumptions!B6*10*Assumptions!B11-Assumptions!B6*Assumptions!B10)) -> 1.9139854 | E9: =(('Operating Model'!G8*$A9-'Debt Schedule'!G8)/(Assumptions!B6*11+Assumptions!B6*11*Assumptions!B11-Assumptions!B6*Assumptions!B10)) -> 1.6001164 | F9: =(('Operating Model'!G8*$A9-'Debt Schedule'!G8)/(Assumptions!B6*12+Assumptions!B6*12*Assumptions!B11-Assumptions!B6*Assumptions!B10)) -> 1.3746857
A12: Caution | B12: Sensitivity grid is a directional screening tool, not a fully recalculated two-variable LBO. It changes entry and exit multiples but holds the base-case debt schedule fixed; a production model should recalculate debt sizing and amortisation for each entry case.

Sheet Model Guide
A1: MODEL GUIDE
A2: Read before using or presenting this workbook
A4: Purpose | B4: Educational LBO screening case for a hypothetical private-equity acquisition of Spire Healthcare Group plc.
A5: Units | B5: GBP millions unless stated. Multiples shown as x; percentages shown as percentages.
A6: Input colour | B6: Yellow cells are key assumptions intended for user review. Blue font denotes formulas.
A7: Public anchors | B7: FY2025 revenue £1,579.8m; FY2025 adjusted EBITDA £268.6m; FY2024 adjusted EBITDA £260.0m; reported FY2025 revenue growth 4.5%. Source: Spire Healthcare 2025 Annual Report and Accounts.
A8: Illustrative assumptions | B8: Entry / exit multiples, leverage, fees, growth, margin expansion, capex, tax, interest and working capital are modelling assumptions, not sourced transaction terms or company guidance.
A9: Key missing work | B9: Extract full 3-year income statement, cash flow, debt, cash, lease liabilities, pension liabilities, capex and segment disclosures from annual reports; create EV-to-equity bridge and full sources & uses; reconcile leases and interest; add downside case and covenant analysis.
A10: Quality control | B10: Open in Excel or LibreOffice to recalculate formulas. Review formulas and replace all screening assumptions before relying on results. Some spreadsheet applications may not calculate until opened.
A11: Disclaimer | B11: This is a student analytical case study, not investment advice, a fairness opinion, a financing commitment or a representation of a real transaction.
