Workbook

Sheet Read Me
A1: TESCO PLC | INTEGRATED MODEL & VALUATION
A2: FY2026 public headline data with illustrative forward assumptions | £m unless stated
A4: PROJECT SCOPE
A5: Objective | B5: Driver-based forecast, simplified unlevered cash flow, DCF, EV/EBITDA cross-check and sensitivities.
A6: Reported anchor | B6: Tesco FY2025/26 preliminary results: sales £66,588m; adjusted operating profit £3,152m; FCF £1,957m; net debt £10,563m.
A7: Model caveat | B7: This is not a full statutory three-statement model. Several operating drivers, share count, WACC, terminal growth, multiple and reference share price are assumptions.
A8: How to use | B8: Review Sources & Assumptions, then Operating Model, DCF & Sensitivity, and Comps & Summary. Yellow cells are editable assumptions.
A9: Sources | B9: https://www.tescoplc.com/preliminary-results-202526 | https://www.tescoplc.com/investors/reports-results-and-presentations/annual-report-2026

Sheet Sources & Assumptions
A1: SOURCES & ASSUMPTIONS
A2: Reported data is green; editable analyst assumptions are yellow.
A4: REPORTED FY2026 HEADLINE DATA
A5: Metric | B5: Value | C5: Units | D5: Source / definition | E5: Status
A6: Sales (ex VAT, ex fuel) | B6: 66588 | C6: £m | D6: Tesco FY2025/26 preliminary results, 52-week comparable basis | E6: Reported
A7: Adjusted operating profit | B7: 3152 | C7: £m | D7: Tesco FY2025/26 preliminary results, comparable basis | E7: Reported
A8: Free cash flow | B8: 1957 | C8: £m | D8: Company-defined APM | E8: Reported
A9: Net debt | B9: 10563 | C9: £m | D9: Company APM at balance-sheet date | E9: Reported
A10: Adjusted diluted EPS | B10: 0.29 | C10: £/share | D10: 29.0p in FY2025/26 results | E10: Reported
A11: Sales growth | B11: 0.046 | C11: % | D11: Company-reported comparable sales growth | E11: Reported
A12: Adjusted operating profit growth | B12: 0.008 | C12: % | D12: Company-reported growth | E12: Reported
A15: ANALYST ASSUMPTIONS — EDITABLE
A16: Assumption | B16: Value | C16: Units | D16: Rationale / caveat | E16: Status
A17: Forecast sales growth | B17: 0.035 | C17: % per year | D17: Moderates recent growth; not company guidance | E17: Analyst assumption
A18: Adjusted operating margin | B18: =B7/B6 -> 0.047335856 | C18: % of sales | D18: Anchored to FY2026 adjusted operating profit / sales | E18: Calculated/reported
A19: D&A | B19: 0.018 | C19: % of sales | D19: Simplified proxy; replace with annual-report detail | E19: Analyst assumption
A20: Capital expenditure | B20: 0.013 | C20: % of sales | D20: Simplified proxy; replace with annual-report detail | E20: Analyst assumption
A21: Change in NWC | B21: 0.002 | C21: % of incremental sales | D21: Illustrative working-capital investment | E21: Analyst assumption
A22: Cash tax rate | B22: 0.25 | C22: % of EBIT | D22: Simplified normalized assumption | E22: Analyst assumption
A23: WACC | B23: 0.075 | C23: % | D23: Illustrative; not calibrated to live market data | E23: Analyst assumption
A24: Terminal growth | B24: 0.02 | C24: % | D24: Long-run growth; must remain below WACC | E24: Analyst assumption
A25: EV / EBITDA multiple | B25: 7 | C25: x | D25: Illustrative cross-check, not a sourced peer median | E25: Analyst assumption
A26: Net debt | B26: 10563 | C26: £m | D26: Reported FY2026 company APM | E26: Calculated/reported
A27: Diluted shares | B27: 6600 | C27: m shares | D27: Illustrative rounded assumption; verify filing | E27: Analyst assumption
A28: Reference share price | B28: 4.2 | C28: £/share | D28: Illustrative reference price, not a live quote | E28: Analyst assumption
A32: Primary source | B32: https://www.tescoplc.com/preliminary-results-202526
A33: Annual report | B33: https://www.tescoplc.com/investors/reports-results-and-presentations/annual-report-2026

Sheet Operating Model
A1: FIVE-YEAR OPERATING MODEL
A2: FY2026 reported anchor; FY2027–FY2031 illustrative forecast | £m
A4: Metric | B4: FY2026A | C4: FY2027E | D4: FY2028E | E4: FY2029E | F4: FY2030E | G4: FY2031E
A5: Sales | B5: ='Sources & Assumptions'!B6 -> 66588 | C5: =B5*(1+'Sources & Assumptions'!$B$17) -> 68918.58 | D5: =C5*(1+'Sources & Assumptions'!$B$17) -> 71330.73 | E5: =D5*(1+'Sources & Assumptions'!$B$17) -> 73827.306 | F5: =E5*(1+'Sources & Assumptions'!$B$17) -> 76411.262 | G5: =F5*(1+'Sources & Assumptions'!$B$17) -> 79085.656
A6: Sales growth | B6: ='Sources & Assumptions'!B11 -> 0.046 | C6: ='Sources & Assumptions'!$B$17 -> 0.035 | D6: ='Sources & Assumptions'!$B$17 -> 0.035 | E6: ='Sources & Assumptions'!$B$17 -> 0.035 | F6: ='Sources & Assumptions'!$B$17 -> 0.035 | G6: ='Sources & Assumptions'!$B$17 -> 0.035
A7: Adjusted operating profit | B7: ='Sources & Assumptions'!B7 -> 3152 | C7: =C5*'Sources & Assumptions'!$B$18 -> 3262.32 | D7: =D5*'Sources & Assumptions'!$B$18 -> 3376.5012 | E7: =E5*'Sources & Assumptions'!$B$18 -> 3494.6787 | F7: =F5*'Sources & Assumptions'!$B$18 -> 3616.9925 | G7: =G5*'Sources & Assumptions'!$B$18 -> 3743.5872
A8: Operating margin | B8: =B7/B5 -> 0.047335856 | C8: =C7/C5 -> 0.047335856 | D8: =D7/D5 -> 0.047335856 | E8: =E7/E5 -> 0.047335856 | F8: =F7/F5 -> 0.047335856 | G8: =G7/G5 -> 0.047335856
A9: D&A | B9: =B5*'Sources & Assumptions'!B19 -> 1198.584 | C9: =C5*'Sources & Assumptions'!$B$19 -> 1240.5344 | D9: =D5*'Sources & Assumptions'!$B$19 -> 1283.9531 | E9: =E5*'Sources & Assumptions'!$B$19 -> 1328.8915 | F9: =F5*'Sources & Assumptions'!$B$19 -> 1375.4027 | G9: =G5*'Sources & Assumptions'!$B$19 -> 1423.5418
A10: EBITDA | B10: =B7+B9 -> 4350.584 | C10: =C7+C9 -> 4502.8544 | D10: =D7+D9 -> 4660.4543 | E10: =E7+E9 -> 4823.5702 | F10: =F7+F9 -> 4992.3952 | G10: =G7+G9 -> 5167.129
A11: Cash taxes | B11: =B7*'Sources & Assumptions'!B22 -> 788 | C11: =C7*'Sources & Assumptions'!$B$22 -> 815.58 | D11: =D7*'Sources & Assumptions'!$B$22 -> 844.1253 | E11: =E7*'Sources & Assumptions'!$B$22 -> 873.66969 | F11: =F7*'Sources & Assumptions'!$B$22 -> 904.24812 | G11: =G7*'Sources & Assumptions'!$B$22 -> 935.89681
A12: NOPAT | B12: =B7-B11 -> 2364 | C12: =C7-C11 -> 2446.74 | D12: =D7-D11 -> 2532.3759 | E12: =E7-E11 -> 2621.0091 | F12: =F7-F11 -> 2712.7444 | G12: =G7-G11 -> 2807.6904
A13: Capital expenditure | B13: =B5*'Sources & Assumptions'!B20 -> 865.644 | C13: =C5*'Sources & Assumptions'!$B$20 -> 895.94154 | D13: =D5*'Sources & Assumptions'!$B$20 -> 927.29949 | E13: =E5*'Sources & Assumptions'!$B$20 -> 959.75498 | F13: =F5*'Sources & Assumptions'!$B$20 -> 993.3464 | G13: =G5*'Sources & Assumptions'!$B$20 -> 1028.1135
A14: Change in NWC | B14: =0 -> 0 | C14: =(C5-B5)*'Sources & Assumptions'!$B$21 -> 4.66116 | D14: =(D5-C5)*'Sources & Assumptions'!$B$21 -> 4.8243006 | E14: =(E5-D5)*'Sources & Assumptions'!$B$21 -> 4.9931511 | F14: =(F5-E5)*'Sources & Assumptions'!$B$21 -> 5.1679114 | G14: =(G5-F5)*'Sources & Assumptions'!$B$21 -> 5.3487883
A15: Unlevered free cash flow | B15: =B12+B9-B13-B14 -> 2696.94 | C15: =C12+C9-C13-C14 -> 2786.6717 | D15: =D12+D9-D13-D14 -> 2884.2053 | E15: =E12+E9-E13-E14 -> 2985.1524 | F15: =F12+F9-F13-F14 -> 3089.6328 | G15: =G12+G9-G13-G14 -> 3197.7699
A16: Illustrative net debt | B16: ='Sources & Assumptions'!B26 -> 10563 | C16: =B16-(C15-(C7*'Sources & Assumptions'!$B$22)) -> 8591.9083 | D16: =C16-(D15-(D7*'Sources & Assumptions'!$B$22)) -> 6551.8283 | E16: =D16-(E15-(E7*'Sources & Assumptions'!$B$22)) -> 4440.3456 | F16: =E16-(F15-(F7*'Sources & Assumptions'!$B$22)) -> 2254.9609 | G16: =F16-(G15-(G7*'Sources & Assumptions'!$B$22)) -> -6.9121935

Sheet DCF & Sensitivity
A1: DCF & SENSITIVITY
A2: Unlevered DCF; assumptions are illustrative, not live market calibration.
A4: DISCOUNTED CASH FLOW
A5: Metric | B5: FY2027E | C5: FY2028E | D5: FY2029E | E5: FY2030E | F5: FY2031E | G5: Terminal
A6: UFCF | B6: ='Operating Model'!C15 -> 2786.6717 | C6: ='Operating Model'!D15 -> 2884.2053 | D6: ='Operating Model'!E15 -> 2985.1524 | E6: ='Operating Model'!F15 -> 3089.6328 | F6: ='Operating Model'!G15 -> 3197.7699 | G6: =F6*(1+'Sources & Assumptions'!$B$24)/('Sources & Assumptions'!$B$23-'Sources & Assumptions'!$B$24) -> 59304.097
A7: Period | B7: 1 | C7: 2 | D7: 3 | E7: 4 | F7: 5 | G7: =F7 -> 5
A8: Discount factor | B8: =1/(1+'Sources & Assumptions'!$B$23)^B7 -> 0.93023256 | C8: =1/(1+'Sources & Assumptions'!$B$23)^C7 -> 0.86533261 | D8: =1/(1+'Sources & Assumptions'!$B$23)^D7 -> 0.80496057 | E8: =1/(1+'Sources & Assumptions'!$B$23)^E7 -> 0.74880053 | F8: =1/(1+'Sources & Assumptions'!$B$23)^F7 -> 0.69655863 | G8: =1/(1+'Sources & Assumptions'!$B$23)^F7 -> 0.69655863
A9: Present value | B9: =B6*B8 -> 2592.2528 | C9: =C6*C8 -> 2495.7969 | D9: =D6*D8 -> 2402.93 | E9: =E6*E8 -> 2313.5187 | F9: =F6*F8 -> 2227.4342 | G9: =G6*G8 -> 41308.78
A12: VALUATION BRIDGE
A13: PV forecast UFCF | B13: =SUM(B9:F9) -> 12031.933
A14: PV terminal value | B14: =G9 -> 41308.78
A15: Enterprise value | B15: =B13+B14 -> 53340.713
A16: Less net debt | B16: ='Sources & Assumptions'!B26 -> 10563
A17: Equity value | B17: =B15-B16 -> 42777.713
A18: Diluted shares (m) | B18: ='Sources & Assumptions'!B27 -> 6600
A19: Implied value/share | B19: =B17/B18 -> 6.4814717
A20: Reference share price | B20: ='Sources & Assumptions'!B28 -> 4.2
A21: Upside / (downside) | B21: =B19/B20-1 -> 0.54320754
A24: WACC / TERMINAL GROWTH SENSITIVITY — IMPLIED VALUE PER SHARE
A25: WACC / g | B25: 0.01 | C25: 0.015 | D25: 0.02 | E25: 0.025 | F25: 0.03
A26: 0.065 | B26: =(('Operating Model'!C15/(1+$A26)^1+'Operating Model'!D15/(1+$A26)^2+'Operating Model'!E15/(1+$A26)^3+'Operating Model'!F15/(1+$A26)^4+'Operating Model'!G15/(1+$A26)^5)+('Operating Model'!G15*(1+B$25)/($A26-B$25))/(1+$A26)^5-'Sources & Assumptions'!$B$26)/'Sources & Assumptions'!$B$27 -> 6.7672622 | C26: =(('Operating Model'!C15/(1+$A26)^1+'Operating Model'!D15/(1+$A26)^2+'Operating Model'!E15/(1+$A26)^3+'Operating Model'!F15/(1+$A26)^4+'Operating Model'!G15/(1+$A26)^5)+('Operating Model'!G15*(1+C$25)/($A26-C$25))/(1+$A26)^5-'Sources & Assumptions'!$B$26)/'Sources & Assumptions'!$B$27 -> 7.4520282 | D26: =(('Operating Model'!C15/(1+$A26)^1+'Operating Model'!D15/(1+$A26)^2+'Operating Model'!E15/(1+$A26)^3+'Operating Model'!F15/(1+$A26)^4+'Operating Model'!G15/(1+$A26)^5)+('Operating Model'!G15*(1+D$25)/($A26-D$25))/(1+$A26)^5-'Sources & Assumptions'!$B$26)/'Sources & Assumptions'!$B$27 -> 8.2889644 | E26: =(('Operating Model'!C15/(1+$A26)^1+'Operating Model'!D15/(1+$A26)^2+'Operating Model'!E15/(1+$A26)^3+'Operating Model'!F15/(1+$A26)^4+'Operating Model'!G15/(1+$A26)^5)+('Operating Model'!G15*(1+E$25)/($A26-E$25))/(1+$A26)^5-'Sources & Assumptions'!$B$26)/'Sources & Assumptions'!$B$27 -> 9.3351346 | F26: =(('Operating Model'!C15/(1+$A26)^1+'Operating Model'!D15/(1+$A26)^2+'Operating Model'!E15/(1+$A26)^3+'Operating Model'!F15/(1+$A26)^4+'Operating Model'!G15/(1+$A26)^5)+('Operating Model'!G15*(1+F$25)/($A26-F$25))/(1+$A26)^5-'Sources & Assumptions'!$B$26)/'Sources & Assumptions'!$B$27 -> 10.680211
A27: 0.07 | B27: =(('Operating Model'!C15/(1+$A27)^1+'Operating Model'!D15/(1+$A27)^2+'Operating Model'!E15/(1+$A27)^3+'Operating Model'!F15/(1+$A27)^4+'Operating Model'!G15/(1+$A27)^5)+('Operating Model'!G15*(1+B$25)/($A27-B$25))/(1+$A27)^5-'Sources & Assumptions'!$B$26)/'Sources & Assumptions'!$B$27 -> 6.0626927 | C27: =(('Operating Model'!C15/(1+$A27)^1+'Operating Model'!D15/(1+$A27)^2+'Operating Model'!E15/(1+$A27)^3+'Operating Model'!F15/(1+$A27)^4+'Operating Model'!G15/(1+$A27)^5)+('Operating Model'!G15*(1+C$25)/($A27-C$25))/(1+$A27)^5-'Sources & Assumptions'!$B$26)/'Sources & Assumptions'!$B$27 -> 6.6227394 | D27: =(('Operating Model'!C15/(1+$A27)^1+'Operating Model'!D15/(1+$A27)^2+'Operating Model'!E15/(1+$A27)^3+'Operating Model'!F15/(1+$A27)^4+'Operating Model'!G15/(1+$A27)^5)+('Operating Model'!G15*(1+D$25)/($A27-D$25))/(1+$A27)^5-'Sources & Assumptions'!$B$26)/'Sources & Assumptions'!$B$27 -> 7.2947954 | E27: =(('Operating Model'!C15/(1+$A27)^1+'Operating Model'!D15/(1+$A27)^2+'Operating Model'!E15/(1+$A27)^3+'Operating Model'!F15/(1+$A27)^4+'Operating Model'!G15/(1+$A27)^5)+('Operating Model'!G15*(1+E$25)/($A27-E$25))/(1+$A27)^5-'Sources & Assumptions'!$B$26)/'Sources & Assumptions'!$B$27 -> 8.1161972 | F27: =(('Operating Model'!C15/(1+$A27)^1+'Operating Model'!D15/(1+$A27)^2+'Operating Model'!E15/(1+$A27)^3+'Operating Model'!F15/(1+$A27)^4+'Operating Model'!G15/(1+$A27)^5)+('Operating Model'!G15*(1+F$25)/($A27-F$25))/(1+$A27)^5-'Sources & Assumptions'!$B$26)/'Sources & Assumptions'!$B$27 -> 9.1429494
A28: 0.075 | B28: =(('Operating Model'!C15/(1+$A28)^1+'Operating Model'!D15/(1+$A28)^2+'Operating Model'!E15/(1+$A28)^3+'Operating Model'!F15/(1+$A28)^4+'Operating Model'!G15/(1+$A28)^5)+('Operating Model'!G15*(1+B$25)/($A28-B$25))/(1+$A28)^5-'Sources & Assumptions'!$B$26)/'Sources & Assumptions'!$B$27 -> 5.4666415 | C28: =(('Operating Model'!C15/(1+$A28)^1+'Operating Model'!D15/(1+$A28)^2+'Operating Model'!E15/(1+$A28)^3+'Operating Model'!F15/(1+$A28)^4+'Operating Model'!G15/(1+$A28)^5)+('Operating Model'!G15*(1+C$25)/($A28-C$25))/(1+$A28)^5-'Sources & Assumptions'!$B$26)/'Sources & Assumptions'!$B$27 -> 5.931772 | D28: =(('Operating Model'!C15/(1+$A28)^1+'Operating Model'!D15/(1+$A28)^2+'Operating Model'!E15/(1+$A28)^3+'Operating Model'!F15/(1+$A28)^4+'Operating Model'!G15/(1+$A28)^5)+('Operating Model'!G15*(1+D$25)/($A28-D$25))/(1+$A28)^5-'Sources & Assumptions'!$B$26)/'Sources & Assumptions'!$B$27 -> 6.4814717 | E28: =(('Operating Model'!C15/(1+$A28)^1+'Operating Model'!D15/(1+$A28)^2+'Operating Model'!E15/(1+$A28)^3+'Operating Model'!F15/(1+$A28)^4+'Operating Model'!G15/(1+$A28)^5)+('Operating Model'!G15*(1+E$25)/($A28-E$25))/(1+$A28)^5-'Sources & Assumptions'!$B$26)/'Sources & Assumptions'!$B$27 -> 7.1411113 | F28: =(('Operating Model'!C15/(1+$A28)^1+'Operating Model'!D15/(1+$A28)^2+'Operating Model'!E15/(1+$A28)^3+'Operating Model'!F15/(1+$A28)^4+'Operating Model'!G15/(1+$A28)^5)+('Operating Model'!G15*(1+F$25)/($A28-F$25))/(1+$A28)^5-'Sources & Assumptions'!$B$26)/'Sources & Assumptions'!$B$27 -> 7.9473375
A29: 0.08 | B29: =(('Operating Model'!C15/(1+$A29)^1+'Operating Model'!D15/(1+$A29)^2+'Operating Model'!E15/(1+$A29)^3+'Operating Model'!F15/(1+$A29)^4+'Operating Model'!G15/(1+$A29)^5)+('Operating Model'!G15*(1+B$25)/($A29-B$25))/(1+$A29)^5-'Sources & Assumptions'!$B$26)/'Sources & Assumptions'!$B$27 -> 4.955852 | C29: =(('Operating Model'!C15/(1+$A29)^1+'Operating Model'!D15/(1+$A29)^2+'Operating Model'!E15/(1+$A29)^3+'Operating Model'!F15/(1+$A29)^4+'Operating Model'!G15/(1+$A29)^5)+('Operating Model'!G15*(1+C$25)/($A29-C$25))/(1+$A29)^5-'Sources & Assumptions'!$B$26)/'Sources & Assumptions'!$B$27 -> 5.3472034 | D29: =(('Operating Model'!C15/(1+$A29)^1+'Operating Model'!D15/(1+$A29)^2+'Operating Model'!E15/(1+$A29)^3+'Operating Model'!F15/(1+$A29)^4+'Operating Model'!G15/(1+$A29)^5)+('Operating Model'!G15*(1+D$25)/($A29-D$25))/(1+$A29)^5-'Sources & Assumptions'!$B$26)/'Sources & Assumptions'!$B$27 -> 5.80378 | E29: =(('Operating Model'!C15/(1+$A29)^1+'Operating Model'!D15/(1+$A29)^2+'Operating Model'!E15/(1+$A29)^3+'Operating Model'!F15/(1+$A29)^4+'Operating Model'!G15/(1+$A29)^5)+('Operating Model'!G15*(1+E$25)/($A29-E$25))/(1+$A29)^5-'Sources & Assumptions'!$B$26)/'Sources & Assumptions'!$B$27 -> 6.3433705 | F29: =(('Operating Model'!C15/(1+$A29)^1+'Operating Model'!D15/(1+$A29)^2+'Operating Model'!E15/(1+$A29)^3+'Operating Model'!F15/(1+$A29)^4+'Operating Model'!G15/(1+$A29)^5)+('Operating Model'!G15*(1+F$25)/($A29-F$25))/(1+$A29)^5-'Sources & Assumptions'!$B$26)/'Sources & Assumptions'!$B$27 -> 6.9908791
A30: 0.085 | B30: =(('Operating Model'!C15/(1+$A30)^1+'Operating Model'!D15/(1+$A30)^2+'Operating Model'!E15/(1+$A30)^3+'Operating Model'!F15/(1+$A30)^4+'Operating Model'!G15/(1+$A30)^5)+('Operating Model'!G15*(1+B$25)/($A30-B$25))/(1+$A30)^5-'Sources & Assumptions'!$B$26)/'Sources & Assumptions'!$B$27 -> 4.5132694 | C30: =(('Operating Model'!C15/(1+$A30)^1+'Operating Model'!D15/(1+$A30)^2+'Operating Model'!E15/(1+$A30)^3+'Operating Model'!F15/(1+$A30)^4+'Operating Model'!G15/(1+$A30)^5)+('Operating Model'!G15*(1+C$25)/($A30-C$25))/(1+$A30)^5-'Sources & Assumptions'!$B$26)/'Sources & Assumptions'!$B$27 -> 4.8462316 | D30: =(('Operating Model'!C15/(1+$A30)^1+'Operating Model'!D15/(1+$A30)^2+'Operating Model'!E15/(1+$A30)^3+'Operating Model'!F15/(1+$A30)^4+'Operating Model'!G15/(1+$A30)^5)+('Operating Model'!G15*(1+D$25)/($A30-D$25))/(1+$A30)^5-'Sources & Assumptions'!$B$26)/'Sources & Assumptions'!$B$27 -> 5.2304189 | E30: =(('Operating Model'!C15/(1+$A30)^1+'Operating Model'!D15/(1+$A30)^2+'Operating Model'!E15/(1+$A30)^3+'Operating Model'!F15/(1+$A30)^4+'Operating Model'!G15/(1+$A30)^5)+('Operating Model'!G15*(1+E$25)/($A30-E$25))/(1+$A30)^5-'Sources & Assumptions'!$B$26)/'Sources & Assumptions'!$B$27 -> 5.6786373 | F30: =(('Operating Model'!C15/(1+$A30)^1+'Operating Model'!D15/(1+$A30)^2+'Operating Model'!E15/(1+$A30)^3+'Operating Model'!F15/(1+$A30)^4+'Operating Model'!G15/(1+$A30)^5)+('Operating Model'!G15*(1+F$25)/($A30-F$25))/(1+$A30)^5-'Sources & Assumptions'!$B$26)/'Sources & Assumptions'!$B$27 -> 6.20835

Sheet Comps & Summary
A1: VALUATION SUMMARY
A2: EV/EBITDA cross-check multiple is illustrative, not a live peer median.
A4: ILLUSTRATIVE EV / EBITDA CROSS-CHECK
A5: Method | B5: EBITDA (£m) | C5: Multiple | D5: EV (£m) | E5: Equity value (£m) | F5: Value/share
A6: EV / EBITDA | B6: ='Operating Model'!G10 -> 5167.129 | C6: ='Sources & Assumptions'!B25 -> 7 | D6: =B6*C6 -> 36169.903 | E6: =D6-'Sources & Assumptions'!B26 -> 25606.903 | F6: =E6/'Sources & Assumptions'!B27 -> 3.8798338
A9: KEY OUTPUTS
A10: DCF implied value/share | B10: ='DCF & Sensitivity'!B19 -> 6.4814717
A11: EV/EBITDA value/share | B11: =F6 -> 3.8798338
A12: Reference share price | B12: ='Sources & Assumptions'!B28 -> 4.2
A13: DCF upside / downside | B13: ='DCF & Sensitivity'!B21 -> 0.54320754
A14: FY2031 EBITDA (£m) | B14: ='Operating Model'!G10 -> 5167.129
A15: FY2031 UFCF (£m) | B15: ='Operating Model'!G15 -> 3197.7699
A18: INVESTMENT CONSIDERATIONS
A19: Scale and customer proposition support resilience, but grocery retail is intensely competitive.
A20: Labour, energy, pricing and capex can pressure margins and free cash flow.
A21: DCF is highly sensitive to WACC, terminal growth, margin and capital intensity.
A22: Lease liabilities and adjusted metric definitions complicate peer comparisons.
A23: Educational framework only; not a buy/sell recommendation.
