Workbook

Sheet Read Me
A1: ILLUSTRATIVE M&A | TESCO / J SAINSBURY
A2: Hypothetical transaction mechanics only. Not a proposed deal or recommendation.
A4: CASE OVERVIEW
A5: Purpose | B5: Demonstrates offer price, purchase price, sources & uses, cash/stock/debt mix, synergies, financing cost and EPS accretion/dilution.
A6: Reported data | B6: Tesco FY26 sales £66,588m, adjusted operating profit £3,152m, net debt £10,563m. Sainsbury FY26 revenue £33,647m, retail underlying operating profit £1,025m, net debt incl. leases £5,743m, underlying EPS 22.3p.
A7: Critical caveat | B7: A Tesco–Sainsbury combination would face exceptional UK competition and regulatory scrutiny. This is a technical modelling case, not a feasible-deal recommendation.
A8: Model limitations | B8: Standalone net income, share prices, share counts, premium, synergies, interest rate and funding assumptions are simplified. Full purchase accounting, detailed refinancing, tax structuring and diligence are excluded.
A9: Sources | B9: Tesco: https://www.tescoplc.com/preliminary-results-202526 | Sainsbury: https://corporate.sainsburys.co.uk/news/press-releases/preliminary-results-for-the-52-weeks-ended-28-february-2026/
A12: WORKBOOK FLOW
A13: 1. Sources & Assumptions: reported headlines and editable transaction inputs.
A14: 2. Purchase Price: offer premium, equity value, cash/stock consideration and new shares.
A15: 3. Sources & Uses: funding bridge and balancing check.
A16: 4. Pro Forma EPS: simplified recurring accretion/dilution and first-year integration-cost impact.
A17: 5. Sensitivity: premium and synergy-realisation sensitivity.

Sheet Sources & Assumptions
A1: PUBLIC DATA & TRANSACTION ASSUMPTIONS
A2: Reported company metrics are distinguished from illustrative analyst assumptions.
A4: REPORTED FY2026 HEADLINE DATA
A5: Metric | B5: Tesco | C5: Sainsbury | D5: Units / source | E5: Status
A6: Sales / revenue | B6: 66588 | C6: 33647 | D6: £m; Tesco comparable sales ex VAT/fuel; Sainsbury group revenue ex VAT incl. fuel | E6: Reported
A7: Adjusted / underlying operating profit | B7: 3152 | C7: 1025 | D7: £m; different company-defined measures | E7: Reported
A8: Net debt | B8: 10563 | C8: 5743 | D8: £m; Sainsbury includes lease liabilities | E8: Reported
A9: Underlying basic EPS | C9: 0.223 | D9: £/share; Sainsbury 22.3p | E9: Reported
A12: TRANSACTION & FINANCING ASSUMPTIONS — EDITABLE
A13: Assumption | B13: Value | C13: Units | D13: Rationale / caveat | E13: Status
A14: Sainsbury unaffected share price | B14: 3 | C14: £/share | D14: Illustrative reference price, not a live quote | E14: Analyst assumption
A15: Offer premium | B15: 0.3 | C15: % | D15: Illustrative offer premium | E15: Analyst assumption
A16: Sainsbury diluted shares | B16: 2300 | C16: m shares | D16: Rounded assumption; verify latest filings | E16: Analyst assumption
A17: Cash consideration | B17: 0.6 | C17: % of purchase price | D17: Remainder funded with Tesco shares | E17: Analyst assumption
A18: Debt-funded share of cash | B18: 0.5 | C18: % of cash consideration | D18: Remaining cash consideration funded with buyer cash | E18: Analyst assumption
A19: Tesco share price | B19: 4.2 | C19: £/share | D19: Illustrative reference price, not a live quote | E19: Analyst assumption
A20: Tesco diluted shares | B20: 6600 | C20: m shares | D20: Rounded modelling assumption | E20: Analyst assumption
A21: Buyer standalone net income | B21: 1900 | C21: £m | D21: Simplified proxy, not statutory net income | E21: Analyst assumption
A22: Target standalone net income | B22: 520 | C22: £m | D22: Illustrative proxy; not directly sourced | E22: Analyst assumption
A23: Annual pre-tax synergies | B23: 450 | C23: £m | D23: Aggressive illustrative run-rate assumption, not company guidance | E23: Analyst assumption
A24: Year-one synergy realisation | B24: 0.75 | C24: % | D24: Illustrative | E24: Analyst assumption
A25: One-off integration costs | B25: 500 | C25: £m | D25: Illustrative; displayed separately | E25: Analyst assumption
... A27: Tax rate | B27: 0.25 | C27: % | D27: Simplified normalized rate | E27: Analyst assumption
A30: Tesco FY2025/26 results | B30: https://www.tescoplc.com/preliminary-results-202526
A31: Sainsbury FY2025/26 results | B31: https://corporate.sainsburys.co.uk/news/press-releases/preliminary-results-for-the-52-weeks-ended-28-february-2026/
A32: Sainsbury FY2026 annual report | B32: https://corporate.sainsburys.co.uk/investors/annual-report-2026/

Sheet Purchase Price
A1: PURCHASE PRICE ANALYSIS
A2: Illustrative share offer and consideration split | £m except per-share data
A4: OFFER VALUE
A5: Unaffected share price | B5: ='Sources & Assumptions'!B14 -> 3 | C5: £/share
A6: Offer premium | B6: ='Sources & Assumptions'!B15 -> 0.3 | C6: %
A7: Offer price per share | B7: =B5*(1+B6) -> 3.9 | C7: £/share
A8: Target diluted shares | B8: ='Sources & Assumptions'!B16 -> 2300 | C8: m
A9: Equity purchase price | B9: =B7*B8 -> 8970 | C9: £m
A10: Cash consideration % | B10: ='Sources & Assumptions'!B17 -> 0.6 | C10: %
A11: Cash consideration | B11: =B9*B10 -> 5382 | C11: £m
A12: Stock consideration | B12: =B9-B11 -> 3588 | C12: £m
A13: Acquirer share price | B13: ='Sources & Assumptions'!B19 -> 4.2 | C13: £/share
A14: New shares issued | B14: =B12/B13 -> 854.28571 | C14: m

Sheet Sources & Uses
A1: SOURCES & USES OF FUNDS
A2: Simplified funding bridge; no target-debt refinancing assumed.
A4: USES
A5: Purchase of target equity | B5: ='Purchase Price'!B9 -> 8970
A6: Fees and expenses (2% of equity value) | B6: ='Purchase Price'!B9*2% -> 179.4
A7: Total uses | B7: =SUM(B5:B6) -> 9149.4
A10: SOURCES
A11: New debt raised | B11: ='Purchase Price'!B11*'Sources & Assumptions'!B18 -> 2691
A12: Acquirer cash | B12: ='Purchase Price'!B11-B11+B6 -> 2870.4
A13: Stock consideration | B13: ='Purchase Price'!B12 -> 3588
A14: Total sources | B14: =SUM(B11:B13) -> 9149.4
A15: Sources less uses (should be zero) | B15: =B14-B7 -> 0

Sheet Pro Forma EPS
A1: PRO FORMA EPS ACCRETION / DILUTION
A2: Simplified recurring EPS analysis; one-off integration costs shown separately.
A4: STANDALONE AND COMBINED EARNINGS
A5: Buyer standalone net income | B5: ='Sources & Assumptions'!B21 -> 1900
A6: Target standalone net income | B6: ='Sources & Assumptions'!B22 -> 520
A7: Annual pre-tax synergies | B7: ='Sources & Assumptions'!B23 -> 450
A8: Year-one synergy realisation | B8: ='Sources & Assumptions'!B24 -> 0.75
A9: Realised pre-tax synergies | B9: =B7*B8 -> 337.5
A10: Tax on synergies | B10: =B9*'Sources & Assumptions'!B27 -> 84.375
A11: After-tax synergies | B11: =B9-B10 -> 253.125
A12: New debt raised | B12: ='Sources & Uses'!B11 -> 2691
A13: Interest expense | B13: =B12*'Sources & Assumptions'!B26 -> 148.005
A14: After-tax interest expense | B14: =B13*(1-'Sources & Assumptions'!B27) -> 111.00375
A15: Pro forma net income | B15: =B5+B6+B11-B14 -> 2562.1213
A16: Buyer shares outstanding (m) | B16: ='Sources & Assumptions'!B20 -> 6600
A17: New shares issued (m) | B17: ='Purchase Price'!B14 -> 854.28571
A18: Pro forma shares outstanding | B18: =B16+B17 -> 7454.2857
A19: Buyer standalone EPS | B19: =B5/B16 -> 0.28787879
A20: Pro forma EPS | B20: =B15/B18 -> 0.34371117
A21: EPS accretion / (dilution) | B21: =B20/B19-1 -> 0.19394406
A22: One-off integration costs, pre-tax | B22: ='Sources & Assumptions'!B25 -> 500
A23: After-tax integration costs | B23: =B22*(1-'Sources & Assumptions'!B27) -> 375
A24: First-year net income after integration | B24: =B15-B23 -> 2187.1213
A25: First-year EPS after integration | B25: =B24/B18 -> 0.29340454

Sheet Sensitivity
A1: EPS ACCRETION / DILUTION SENSITIVITY
A2: Sensitivity varies offer premium and synergy realisation; simplified earnings framework.
A4: OFFER PREMIUM VS SYNERGY REALISATION
A5: Premium / Synergy | B5: 25% | C5: 50% | D5: 75% | E5: 100% | F5: 125%
A6: 0.15 | B6: =((('Sources & Assumptions'!$B$21+'Sources & Assumptions'!$B$22+('Sources & Assumptions'!$B$23*B$5*(1-'Sources & Assumptions'!$B$27))-(((('Sources & Assumptions'!$B$14*(1+$A6)*'Sources & Assumptions'!$B$16)*'Sources & Assumptions'!$B$17)*'Sources & Assumptions'!$B$18)*'Sources & Assumptions'!$B$26*(1-'Sources & Assumptions'!$B$27)))/('Sources & Assumptions'!$B$20+((('Sources & Assumptions'!$B$14*(1+$A6)*'Sources & Assumptions'!$B$16)-(('Sources & Assumptions'!$B$14*(1+$A6)*'Sources & Assumptions'!$B$16)*'Sources & Assumptions'!$B$17))/'Sources & Assumptions'!$B$19)))/('Sources & Assumptions'!$B$21/'Sources & Assumptions'!$B$20))-1 -> 0.13630125 | C6: =((('Sources & Assumptions'!$B$21+'Sources & Assumptions'!$B$22+('Sources & Assumptions'!$B$23*C$5*(1-'Sources & Assumptions'!$B$27))-(((('Sources & Assumptions'!$B$14*(1+$A6)*'Sources & Assumptions'!$B$16)*'Sources & Assumptions'!$B$17)*'Sources & Assumptions'!$B$18)*'Sources & Assumptions'!$B$26*(1-'Sources & Assumptions'!$B$27)))/('Sources & Assumptions'!$B$20+((('Sources & Assumptions'!$B$14*(1+$A6)*'Sources & Assumptions'!$B$16)-(('Sources & Assumptions'!$B$14*(1+$A6)*'Sources & Assumptions'!$B$16)*'Sources & Assumptions'!$B$17))/'Sources & Assumptions'!$B$19)))/('Sources & Assumptions'!$B$21/'Sources & Assumptions'!$B$20))-1 -> 0.17614674 | D6: =((('Sources & Assumptions'!$B$21+'Sources & Assumptions'!$B$22+('Sources & Assumptions'!$B$23*D$5*(1-'Sources & Assumptions'!$B$27))-(((('Sources & Assumptions'!$B$14*(1+$A6)*'Sources & Assumptions'!$B$16)*'Sources & Assumptions'!$B$17)*'Sources & Assumptions'!$B$18)*'Sources & Assumptions'!$B$26*(1-'Sources & Assumptions'!$B$27)))/('Sources & Assumptions'!$B$20+((('Sources & Assumptions'!$B$14*(1+$A6)*'Sources & Assumptions'!$B$16)-(('Sources & Assumptions'!$B$14*(1+$A6)*'Sources & Assumptions'!$B$16)*'Sources & Assumptions'!$B$17))/'Sources & Assumptions'!$B$19)))/('Sources & Assumptions'!$B$21/'Sources & Assumptions'!$B$20))-1 -> 0.21599224 | E6: =((('Sources & Assumptions'!$B$21+'Sources & Assumptions'!$B$22+('Sources & Assumptions'!$B$23*E$5*(1-'Sources & Assumptions'!$B$27))-(((('Sources & Assumptions'!$B$14*(1+$A6)*'Sources & Assumptions'!$B$16)*'Sources & Assumptions'!$B$17)*'Sources & Assumptions'!$B$18)*'Sources & Assumptions'!$B$26*(1-'Sources & Assumptions'!$B$27)))/('Sources & Assumptions'!$B$20+((('Sources & Assumptions'!$B$14*(1+$A6)*'Sources & Assumptions'!$B$16)-(('Sources & Assumptions'!$B$14*(1+$A6)*'Sources & Assumptions'!$B$16)*'Sources & Assumptions'!$B$17))/'Sources & Assumptions'!$B$19)))/('Sources & Assumptions'!$B$21/'Sources & Assumptions'!$B$20))-1 -> 0.25583774 | F6: =((('Sources & Assumptions'!$B$21+'Sources & Assumptions'!$B$22+('Sources & Assumptions'!$B$23*F$5*(1-'Sources & Assumptions'!$B$27))-(((('Sources & Assumptions'!$B$14*(1+$A6)*'Sources & Assumptions'!$B$16)*'Sources & Assumptions'!$B$17)*'Sources & Assumptions'!$B$18)*'Sources & Assumptions'!$B$26*(1-'Sources & Assumptions'!$B$27)))/('Sources & Assumptions'!$B$20+((('Sources & Assumptions'!$B$14*(1+$A6)*'Sources & Assumptions'!$B$16)-(('Sources & Assumptions'!$B$14*(1+$A6)*'Sources & Assumptions'!$B$16)*'Sources & Assumptions'!$B$17))/'Sources & Assumptions'!$B$19)))/('Sources & Assumptions'!$B$21/'Sources & Assumptions'!$B$20))-1 -> 0.29568324
A7: 0.2 | B7: =((('Sources & Assumptions'!$B$21+'Sources & Assumptions'!$B$22+('Sources & Assumptions'!$B$23*B$5*(1-'Sources & Assumptions'!$B$27))-(((('Sources & Assumptions'!$B$14*(1+$A7)*'Sources & Assumptions'!$B$16)*'Sources & Assumptions'!$B$17)*'Sources & Assumptions'!$B$18)*'Sources & Assumptions'!$B$26*(1-'Sources & Assumptions'!$B$27)))/('Sources & Assumptions'!$B$20+((('Sources & Assumptions'!$B$14*(1+$A7)*'Sources & Assumptions'!$B$16)-(('Sources & Assumptions'!$B$14*(1+$A7)*'Sources & Assumptions'!$B$16)*'Sources & Assumptions'!$B$17))/'Sources & Assumptions'!$B$19)))/('Sources & Assumptions'!$B$21/'Sources & Assumptions'!$B$20))-1 -> 0.12924087 | C7: =((('Sources & Assumptions'!$B$21+'Sources & Assumptions'!$B$22+('Sources & Assumptions'!$B$23*C$5*(1-'Sources & Assumptions'!$B$27))-(((('Sources & Assumptions'!$B$14*(1+$A7)*'Sources & Assumptions'!$B$16)*'Sources & Assumptions'!$B$17)*'Sources & Assumptions'!$B$18)*'Sources & Assumptions'!$B$26*(1-'Sources & Assumptions'!$B$27)))/('Sources & Assumptions'!$B$20+((('Sources & Assumptions'!$B$14*(1+$A7)*'Sources & Assumptions'!$B$16)-(('Sources & Assumptions'!$B$14*(1+$A7)*'Sources & Assumptions'!$B$16)*'Sources & Assumptions'!$B$17))/'Sources & Assumptions'!$B$19)))/('Sources & Assumptions'!$B$21/'Sources & Assumptions'!$B$20))-1 -> 0.16890918 | D7: =((('Sources & Assumptions'!$B$21+'Sources & Assumptions'!$B$22+('Sources & Assumptions'!$B$23*D$5*(1-'Sources & Assumptions'!$B$27))-(((('Sources & Assumptions'!$B$14*(1+$A7)*'Sources & Assumptions'!$B$16)*'Sources & Assumptions'!$B$17)*'Sources & Assumptions'!$B$18)*'Sources & Assumptions'!$B$26*(1-'Sources & Assumptions'!$B$27)))/('Sources & Assumptions'!$B$20+((('Sources & Assumptions'!$B$14*(1+$A7)*'Sources & Assumptions'!$B$16)-(('Sources & Assumptions'!$B$14*(1+$A7)*'Sources & Assumptions'!$B$16)*'Sources & Assumptions'!$B$17))/'Sources & Assumptions'!$B$19)))/('Sources & Assumptions'!$B$21/'Sources & Assumptions'!$B$20))-1 -> 0.20857748 | E7: =((('Sources & Assumptions'!$B$21+'Sources & Assumptions'!$B$22+('Sources & Assumptions'!$B$23*E$5*(1-'Sources & Assumptions'!$B$27))-(((('Sources & Assumptions'!$B$14*(1+$A7)*'Sources & Assumptions'!$B$16)*'Sources & Assumptions'!$B$17)*'Sources & Assumptions'!$B$18)*'Sources & Assumptions'!$B$26*(1-'Sources & Assumptions'!$B$27)))/('Sources & Assumptions'!$B$20+((('Sources & Assumptions'!$B$14*(1+$A7)*'Sources & Assumptions'!$B$16)-(('Sources & Assumptions'!$B$14*(1+$A7)*'Sources & Assumptions'!$B$16)*'Sources & Assumptions'!$B$17))/'Sources & Assumptions'!$B$19)))/('Sources & Assumptions'!$B$21/'Sources & Assumptions'!$B$20))-1 -> 0.24824579 | F7: =((('Sources & Assumptions'!$B$21+'Sources & Assumptions'!$B$22+('Sources & Assumptions'!$B$23*F$5*(1-'Sources & Assumptions'!$B$27))-(((('Sources & Assumptions'!$B$14*(1+$A7)*'Sources & Assumptions'!$B$16)*'Sources & Assumptions'!$B$17)*'Sources & Assumptions'!$B$18)*'Sources & Assumptions'!$B$26*(1-'Sources & Assumptions'!$B$27)))/('Sources & Assumptions'!$B$20+((('Sources & Assumptions'!$B$14*(1+$A7)*'Sources & Assumptions'!$B$16)-(('Sources & Assumptions'!$B$14*(1+$A7)*'Sources & Assumptions'!$B$16)*'Sources & Assumptions'!$B$17))/'Sources & Assumptions'!$B$19)))/('Sources & Assumptions'!$B$21/'Sources & Assumptions'!$B$20))-1 -> 0.28791409
A8: 0.25 | B8: =((('Sources & Assumptions'!$B$21+'Sources & Assumptions'!$B$22+('Sources & Assumptions'!$B$23*B$5*(1-'Sources & Assumptions'!$B$27))-(((('Sources & Assumptions'!$B$14*(1+$A8)*'Sources & Assumptions'!$B$16)*'Sources & Assumptions'!$B$17)*'Sources & Assumptions'!$B$18)*'Sources & Assumptions'!$B$26*(1-'Sources & Assumptions'!$B$27)))/('Sources & Assumptions'!$B$20+((('Sources & Assumptions'!$B$14*(1+$A8)*'Sources & Assumptions'!$B$16)-(('Sources & Assumptions'!$B$14*(1+$A8)*'Sources & Assumptions'!$B$16)*'Sources & Assumptions'!$B$17))/'Sources & Assumptions'!$B$19)))/('Sources & Assumptions'!$B$21/'Sources & Assumptions'!$B$20))-1 -> 0.12224302 | C8: =((('Sources & Assumptions'!$B$21+'Sources & Assumptions'!$B$22+('Sources & Assumptions'!$B$23*C$5*(1-'Sources & Assumptions'!$B$27))-(((('Sources & Assumptions'!$B$14*(1+$A8)*'Sources & Assumptions'!$B$16)*'Sources & Assumptions'!$B$17)*'Sources & Assumptions'!$B$18)*'Sources & Assumptions'!$B$26*(1-'Sources & Assumptions'!$B$27)))/('Sources & Assumptions'!$B$20+((('Sources & Assumptions'!$B$14*(1+$A8)*'Sources & Assumptions'!$B$16)-(('Sources & Assumptions'!$B$14*(1+$A8)*'Sources & Assumptions'!$B$16)*'Sources & Assumptions'!$B$17))/'Sources & Assumptions'!$B$19)))/('Sources & Assumptions'!$B$21/'Sources & Assumptions'!$B$20))-1 -> 0.1617357 | D8: =((('Sources & Assumptions'!$B$21+'Sources & Assumptions'!$B$22+('Sources & Assumptions'!$B$23*D$5*(1-'Sources & Assumptions'!$B$27))-(((('Sources & Assumptions'!$B$14*(1+$A8)*'Sources & Assumptions'!$B$16)*'Sources & Assumptions'!$B$17)*'Sources & Assumptions'!$B$18)*'Sources & Assumptions'!$B$26*(1-'Sources & Assumptions'!$B$27)))/('Sources & Assumptions'!$B$20+((('Sources & Assumptions'!$B$14*(1+$A8)*'Sources & Assumptions'!$B$16)-(('Sources & Assumptions'!$B$14*(1+$A8)*'Sources & Assumptions'!$B$16)*'Sources & Assumptions'!$B$17))/'Sources & Assumptions'!$B$19)))/('Sources & Assumptions'!$B$21/'Sources & Assumptions'!$B$20))-1 -> 0.20122838 | E8: =((('Sources & Assumptions'!$B$21+'Sources & Assumptions'!$B$22+('Sources & Assumptions'!$B$23*E$5*(1-'Sources & Assumptions'!$B$27))-(((('Sources & Assumptions'!$B$14*(1+$A8)*'Sources & Assumptions'!$B$16)*'Sources & Assumptions'!$B$17)*'Sources & Assumptions'!$B$18)*'Sources & Assumptions'!$B$26*(1-'Sources & Assumptions'!$B$27)))/('Sources & Assumptions'!$B$20+((('Sources & Assumptions'!$B$14*(1+$A8)*'Sources & Assumptions'!$B$16)-(('Sources & Assumptions'!$B$14*(1+$A8)*'Sources & Assumptions'!$B$16)*'Sources & Assumptions'!$B$17))/'Sources & Assumptions'!$B$19)))/('Sources & Assumptions'!$B$21/'Sources & Assumptions'!$B$20))-1 -> 0.24072106 | F8: =((('Sources & Assumptions'!$B$21+'Sources & Assumptions'!$B$22+('Sources & Assumptions'!$B$23*F$5*(1-'Sources & Assumptions'!$B$27))-(((('Sources & Assumptions'!$B$14*(1+$A8)*'Sources & Assumptions'!$B$16)*'Sources & Assumptions'!$B$17)*'Sources & Assumptions'!$B$18)*'Sources & Assumptions'!$B$26*(1-'Sources & Assumptions'!$B$27)))/('Sources & Assumptions'!$B$20+((('Sources & Assumptions'!$B$14*(1+$A8)*'Sources & Assumptions'!$B$16)-(('Sources & Assumptions'!$B$14*(1+$A8)*'Sources & Assumptions'!$B$16)*'Sources & Assumptions'!$B$17))/'Sources & Assumptions'!$B$19)))/('Sources & Assumptions'!$B$21/'Sources & Assumptions'!$B$20))-1 -> 0.28021374
A9: 0.3 | B9: =((('Sources & Assumptions'!$B$21+'Sources & Assumptions'!$B$22+('Sources & Assumptions'!$B$23*B$5*(1-'Sources & Assumptions'!$B$27))-(((('Sources & Assumptions'!$B$14*(1+$A9)*'Sources & Assumptions'!$B$16)*'Sources & Assumptions'!$B$17)*'Sources & Assumptions'!$B$18)*'Sources & Assumptions'!$B$26*(1-'Sources & Assumptions'!$B$27)))/('Sources & Assumptions'!$B$20+((('Sources & Assumptions'!$B$14*(1+$A9)*'Sources & Assumptions'!$B$16)-(('Sources & Assumptions'!$B$14*(1+$A9)*'Sources & Assumptions'!$B$16)*'Sources & Assumptions'!$B$17))/'Sources & Assumptions'!$B$19)))/('Sources & Assumptions'!$B$21/'Sources & Assumptions'!$B$20))-1 -> 0.11530685 | C9: =((('Sources & Assumptions'!$B$21+'Sources & Assumptions'!$B$22+('Sources & Assumptions'!$B$23*C$5*(1-'Sources & Assumptions'!$B$27))-(((('Sources & Assumptions'!$B$14*(1+$A9)*'Sources & Assumptions'!$B$16)*'Sources & Assumptions'!$B$17)*'Sources & Assumptions'!$B$18)*'Sources & Assumptions'!$B$26*(1-'Sources & Assumptions'!$B$27)))/('Sources & Assumptions'!$B$20+((('Sources & Assumptions'!$B$14*(1+$A9)*'Sources & Assumptions'!$B$16)-(('Sources & Assumptions'!$B$14*(1+$A9)*'Sources & Assumptions'!$B$16)*'Sources & Assumptions'!$B$17))/'Sources & Assumptions'!$B$19)))/('Sources & Assumptions'!$B$21/'Sources & Assumptions'!$B$20))-1 -> 0.15462545 | D9: =((('Sources & Assumptions'!$B$21+'Sources & Assumptions'!$B$22+('Sources & Assumptions'!$B$23*D$5*(1-'Sources & Assumptions'!$B$27))-(((('Sources & Assumptions'!$B$14*(1+$A9)*'Sources & Assumptions'!$B$16)*'Sources & Assumptions'!$B$17)*'Sources & Assumptions'!$B$18)*'Sources & Assumptions'!$B$26*(1-'Sources & Assumptions'!$B$27)))/('Sources & Assumptions'!$B$20+((('Sources & Assumptions'!$B$14*(1+$A9)*'Sources & Assumptions'!$B$16)-(('Sources & Assumptions'!$B$14*(1+$A9)*'Sources & Assumptions'!$B$16)*'Sources & Assumptions'!$B$17))/'Sources & Assumptions'!$B$19)))/('Sources & Assumptions'!$B$21/'Sources & Assumptions'!$B$20))-1 -> 0.19394406 | E9: =((('Sources & Assumptions'!$B$21+'Sources & Assumptions'!$B$22+('Sources & Assumptions'!$B$23*E$5*(1-'Sources & Assumptions'!$B$27))-(((('Sources & Assumptions'!$B$14*(1+$A9)*'Sources & Assumptions'!$B$16)*'Sources & Assumptions'!$B$17)*'Sources & Assumptions'!$B$18)*'Sources & Assumptions'!$B$26*(1-'Sources & Assumptions'!$B$27)))/('Sources & Assumptions'!$B$20+((('Sources & Assumptions'!$B$14*(1+$A9)*'Sources & Assumptions'!$B$16)-(('Sources & Assumptions'!$B$14*(1+$A9)*'Sources & Assumptions'!$B$16)*'Sources & Assumptions'!$B$17))/'Sources & Assumptions'!$B$19)))/('Sources & Assumptions'!$B$21/'Sources & Assumptions'!$B$20))-1 -> 0.23326266 | F9: =((('Sources & Assumptions'!$B$21+'Sources & Assumptions'!$B$22+('Sources & Assumptions'!$B$23*F$5*(1-'Sources & Assumptions'!$B$27))-(((('Sources & Assumptions'!$B$14*(1+$A9)*'Sources & Assumptions'!$B$16)*'Sources & Assumptions'!$B$17)*'Sources & Assumptions'!$B$18)*'Sources & Assumptions'!$B$26*(1-'Sources & Assumptions'!$B$27)))/('Sources & Assumptions'!$B$20+((('Sources & Assumptions'!$B$14*(1+$A9)*'Sources & Assumptions'!$B$16)-(('Sources & Assumptions'!$B$14*(1+$A9)*'Sources & Assumptions'!$B$16)*'Sources & Assumptions'!$B$17))/'Sources & Assumptions'!$B$19)))/('Sources & Assumptions'!$B$21/'Sources & Assumptions'!$B$20))-1 -> 0.27258126
A10: 0.35 | B10: =((('Sources & Assumptions'!$B$21+'Sources & Assumptions'!$B$22+('Sources & Assumptions'!$B$23*B$5*(1-'Sources & Assumptions'!$B$27))-(((('Sources & Assumptions'!$B$14*(1+$A10)*'Sources & Assumptions'!$B$16)*'Sources & Assumptions'!$B$17)*'Sources & Assumptions'!$B$18)*'Sources & Assumptions'!$B$26*(1-'Sources & Assumptions'!$B$27)))/('Sources & Assumptions'!$B$20+((('Sources & Assumptions'!$B$14*(1+$A10)*'Sources & Assumptions'!$B$16)-(('Sources & Assumptions'!$B$14*(1+$A10)*'Sources & Assumptions'!$B$16)*'Sources & Assumptions'!$B$17))/'Sources & Assumptions'!$B$19)))/('Sources & Assumptions'!$B$21/'Sources & Assumptions'!$B$20))-1 -> 0.10843156 | C10: =((('Sources & Assumptions'!$B$21+'Sources & Assumptions'!$B$22+('Sources & Assumptions'!$B$23*C$5*(1-'Sources & Assumptions'!$B$27))-(((('Sources & Assumptions'!$B$14*(1+$A10)*'Sources & Assumptions'!$B$16)*'Sources & Assumptions'!$B$17)*'Sources & Assumptions'!$B$18)*'Sources & Assumptions'!$B$26*(1-'Sources & Assumptions'!$B$27)))/('Sources & Assumptions'!$B$20+((('Sources & Assumptions'!$B$14*(1+$A10)*'Sources & Assumptions'!$B$16)-(('Sources & Assumptions'!$B$14*(1+$A10)*'Sources & Assumptions'!$B$16)*'Sources & Assumptions'!$B$17))/'Sources & Assumptions'!$B$19)))/('Sources & Assumptions'!$B$21/'Sources & Assumptions'!$B$20))-1 -> 0.14757762 | D10: =((('Sources & Assumptions'!$B$21+'Sources & Assumptions'!$B$22+('Sources & Assumptions'!$B$23*D$5*(1-'Sources & Assumptions'!$B$27))-(((('Sources & Assumptions'!$B$14*(1+$A10)*'Sources & Assumptions'!$B$16)*'Sources & Assumptions'!$B$17)*'Sources & Assumptions'!$B$18)*'Sources & Assumptions'!$B$26*(1-'Sources & Assumptions'!$B$27)))/('Sources & Assumptions'!$B$20+((('Sources & Assumptions'!$B$14*(1+$A10)*'Sources & Assumptions'!$B$16)-(('Sources & Assumptions'!$B$14*(1+$A10)*'Sources & Assumptions'!$B$16)*'Sources & Assumptions'!$B$17))/'Sources & Assumptions'!$B$19)))/('Sources & Assumptions'!$B$21/'Sources & Assumptions'!$B$20))-1 -> 0.18672367 | E10: =((('Sources & Assumptions'!$B$21+'Sources & Assumptions'!$B$22+('Sources & Assumptions'!$B$23*E$5*(1-'Sources & Assumptions'!$B$27))-(((('Sources & Assumptions'!$B$14*(1+$A10)*'Sources & Assumptions'!$B$16)*'Sources & Assumptions'!$B$17)*'Sources & Assumptions'!$B$18)*'Sources & Assumptions'!$B$26*(1-'Sources & Assumptions'!$B$27)))/('Sources & Assumptions'!$B$20+((('Sources & Assumptions'!$B$14*(1+$A10)*'Sources & Assumptions'!$B$16)-(('Sources & Assumptions'!$B$14*(1+$A10)*'Sources & Assumptions'!$B$16)*'Sources & Assumptions'!$B$17))/'Sources & Assumptions'!$B$19)))/('Sources & Assumptions'!$B$21/'Sources & Assumptions'!$B$20))-1 -> 0.22586973 | F10: =((('Sources & Assumptions'!$B$21+'Sources & Assumptions'!$B$22+('Sources & Assumptions'!$B$23*F$5*(1-'Sources & Assumptions'!$B$27))-(((('Sources & Assumptions'!$B$14*(1+$A10)*'Sources & Assumptions'!$B$16)*'Sources & Assumptions'!$B$17)*'Sources & Assumptions'!$B$18)*'Sources & Assumptions'!$B$26*(1-'Sources & Assumptions'!$B$27)))/('Sources & Assumptions'!$B$20+((('Sources & Assumptions'!$B$14*(1+$A10)*'Sources & Assumptions'!$B$16)-(('Sources & Assumptions'!$B$14*(1+$A10)*'Sources & Assumptions'!$B$16)*'Sources & Assumptions'!$B$17))/'Sources & Assumptions'!$B$19)))/('Sources & Assumptions'!$B$21/'Sources & Assumptions'!$B$20))-1 -> 0.26501578
A11: 0.4 | B11: =((('Sources & Assumptions'!$B$21+'Sources & Assumptions'!$B$22+('Sources & Assumptions'!$B$23*B$5*(1-'Sources & Assumptions'!$B$27))-(((('Sources & Assumptions'!$B$14*(1+$A11)*'Sources & Assumptions'!$B$16)*'Sources & Assumptions'!$B$17)*'Sources & Assumptions'!$B$18)*'Sources & Assumptions'!$B$26*(1-'Sources & Assumptions'!$B$27)))/('Sources & Assumptions'!$B$20+((('Sources & Assumptions'!$B$14*(1+$A11)*'Sources & Assumptions'!$B$16)-(('Sources & Assumptions'!$B$14*(1+$A11)*'Sources & Assumptions'!$B$16)*'Sources & Assumptions'!$B$17))/'Sources & Assumptions'!$B$19)))/('Sources & Assumptions'!$B$21/'Sources & Assumptions'!$B$20))-1 -> 0.10161636 | C11: =((('Sources & Assumptions'!$B$21+'Sources & Assumptions'!$B$22+('Sources & Assumptions'!$B$23*C$5*(1-'Sources & Assumptions'!$B$27))-(((('Sources & Assumptions'!$B$14*(1+$A11)*'Sources & Assumptions'!$B$16)*'Sources & Assumptions'!$B$17)*'Sources & Assumptions'!$B$18)*'Sources & Assumptions'!$B$26*(1-'Sources & Assumptions'!$B$27)))/('Sources & Assumptions'!$B$20+((('Sources & Assumptions'!$B$14*(1+$A11)*'Sources & Assumptions'!$B$16)-(('Sources & Assumptions'!$B$14*(1+$A11)*'Sources & Assumptions'!$B$16)*'Sources & Assumptions'!$B$17))/'Sources & Assumptions'!$B$19)))/('Sources & Assumptions'!$B$21/'Sources & Assumptions'!$B$20))-1 -> 0.14059137 | D11: =((('Sources & Assumptions'!$B$21+'Sources & Assumptions'!$B$22+('Sources & Assumptions'!$B$23*D$5*(1-'Sources & Assumptions'!$B$27))-(((('Sources & Assumptions'!$B$14*(1+$A11)*'Sources & Assumptions'!$B$16)*'Sources & Assumptions'!$B$17)*'Sources & Assumptions'!$B$18)*'Sources & Assumptions'!$B$26*(1-'Sources & Assumptions'!$B$27)))/('Sources & Assumptions'!$B$20+((('Sources & Assumptions'!$B$14*(1+$A11)*'Sources & Assumptions'!$B$16)-(('Sources & Assumptions'!$B$14*(1+$A11)*'Sources & Assumptions'!$B$16)*'Sources & Assumptions'!$B$17))/'Sources & Assumptions'!$B$19)))/('Sources & Assumptions'!$B$21/'Sources & Assumptions'!$B$20))-1 -> 0.17956638 | E11: =((('Sources & Assumptions'!$B$21+'Sources & Assumptions'!$B$22+('Sources & Assumptions'!$B$23*E$5*(1-'Sources & Assumptions'!$B$27))-(((('Sources & Assumptions'!$B$14*(1+$A11)*'Sources & Assumptions'!$B$16)*'Sources & Assumptions'!$B$17)*'Sources & Assumptions'!$B$18)*'Sources & Assumptions'!$B$26*(1-'Sources & Assumptions'!$B$27)))/('Sources & Assumptions'!$B$20+((('Sources & Assumptions'!$B$14*(1+$A11)*'Sources & Assumptions'!$B$16)-(('Sources & Assumptions'!$B$14*(1+$A11)*'Sources & Assumptions'!$B$16)*'Sources & Assumptions'!$B$17))/'Sources & Assumptions'!$B$19)))/('Sources & Assumptions'!$B$21/'Sources & Assumptions'!$B$20))-1 -> 0.2185414 | F11: =((('Sources & Assumptions'!$B$21+'Sources & Assumptions'!$B$22+('Sources & Assumptions'!$B$23*F$5*(1-'Sources & Assumptions'!$B$27))-(((('Sources & Assumptions'!$B$14*(1+$A11)*'Sources & Assumptions'!$B$16)*'Sources & Assumptions'!$B$17)*'Sources & Assumptions'!$B$18)*'Sources & Assumptions'!$B$26*(1-'Sources & Assumptions'!$B$27)))/('Sources & Assumptions'!$B$20+((('Sources & Assumptions'!$B$14*(1+$A11)*'Sources & Assumptions'!$B$16)-(('Sources & Assumptions'!$B$14*(1+$A11)*'Sources & Assumptions'!$B$16)*'Sources & Assumptions'!$B$17))/'Sources & Assumptions'!$B$19)))/('Sources & Assumptions'!$B$21/'Sources & Assumptions'!$B$20))-1 -> 0.25751641
A14: Interpretation | B14: Accretion depends on offer premium, synergies, debt funding cost and new shares. Regulatory and execution risks are not quantified.
